pypozyx/__init__.py
pypozyx/core.py
pypozyx/lib.py
pypozyx/pozyx_i2c.py
pypozyx/pozyx_serial.py
pypozyx/definitions/__init__.py
pypozyx/definitions/bitmasks.py
pypozyx/definitions/constants.py
pypozyx/definitions/registers.py
pypozyx/structures/__init__.py
pypozyx/structures/byte_structure.py
pypozyx/structures/device.py
pypozyx/structures/device_information.py
pypozyx/structures/generic.py
pypozyx/structures/sensor_data.py
pypozyx/tools/__init__.py
pypozyx/tools/device_list.py
pypozyx/tools/discovery.py
pypozyx/tools/version_check.py
pypozyx_i2c-1.3.10.dist-info/DESCRIPTION.rst
pypozyx_i2c-1.3.10.dist-info/METADATA
pypozyx_i2c-1.3.10.dist-info/RECORD
pypozyx_i2c-1.3.10.dist-info/WHEEL
pypozyx_i2c-1.3.10.dist-info/metadata.json
pypozyx_i2c-1.3.10.dist-info/top_level.txt
